jsonwhatever/__init__.py
jsonwhatever/jsonwhatever.py
jsonwhatever/test.py
jsonwhatever-1.1.1.dist-info/METADATA
jsonwhatever-1.1.1.dist-info/WHEEL
jsonwhatever-1.1.1.dist-info/top_level.txt
jsonwhatever-1.1.1.dist-info/RECORD
