Metadata-Version: 2.1
Name: jsonwhatever
Version: 1.1.1
Summary: A simple JSON string creator that takes whatever you have and transform it into a String
Home-page: UNKNOWN
Author: dazjuancarlos
Author-email: dazjuancarlos@gmail.com
License: MIT
Keywords: python,json,simple
Platform: UNKNOWN
Classifier: Development Status :: 5 - Production/Stable
Classifier: Intended Audience :: Developers
Classifier: Programming Language :: Python :: 3
Classifier: Operating System :: Unix
Classifier: Operating System :: MacOS :: MacOS X
Classifier: Operating System :: Microsoft :: Windows
